{"transfers_out": 217131, "code": 23277, "event_total": 0, "last_season_points": 0, "squad_number": null, "transfers_balance": 5685, "news_updated": "2012-04-06T13:30:29 UTC+0000", "event_cost": 110, "news_added": "2012-04-06T12:30:29 UTC+0000", "web_name": "Lampard", "in_dreamteam": false, "team_code": 23277, "id": 102, "shirt_image_url": "http://cdn.ismfg.net/static/plfpl/img/shirts/shirt_5.png", "first_name": "Frank", "transfers_out_event": 79, "element_type_id": 3, "max_cost": 120, "event_explain": [["Minutes played", 0, 0]], "selected": 75935, "min_cost": 110, "fixtures": {"all": [], "summary": []}, "season_history": [["2006/07", 3244, 11, 12, 0, 23, 0, 0, 1, 3, 0, 0, 23, 0, 115, 202], ["2007/08", 1954, 10, 10, 0, 14, 0, 0, 0, 4, 1, 0, 19, 0, 111, 149], ["2008/09", 3256, 12, 10, 0, 19, 0, 0, 0, 3, 1, 0, 46, 0, 121, 226], ["2009/10", 3218, 22, 17, 0, 32, 0, 0, 1, 0, 0, 0, 37, 0, 136, 284], ["2010/11", 2024, 10, 4, 9, 21, 0, 0, 1, 2, 0, 0, 16, 0, 130, 130]], "total_points": 138, "type_name": "Midfielder", "team_name": "Chelsea", "status": "a", "added": "2011-07-14T10:25:54 UTC+0000", "form": 0.8, "shirt_mobile_image_url": "http://cdn.ismfg.net/static/plfpl/img/shirts/mobile/shirt_5.png", "current_fixture": "Blackburn (H)", "now_cost": 110, "points_per_game": 4.6, "transfers_in": 189900, "news": "", "original_cost": 120, "event_points": 0, "news_return": null, "fixture_history": {"all": [["14 Aug", 1, "STO(A) 0-0", 90, 0, 0, 1, 0, 0, 0, 0, 1, 0, 0, 0, 11, 0, 120, 2], ["20 Aug", 2, "WBA(H) 2-1", 90, 0, 1, 0, 1, 0, 0, 0, 1, 0, 0, 0, 6, 0, 120, 4], ["27 Aug", 3, "NOR(H) 3-1", 90, 1, 1, 0, 1, 0, 0, 0, 0, 0, 0, 3, 32, -282, 120, 13], ["10 Sep", 4, "SUN(A) 2-1", 90, 0, 0, 0, 1, 0, 0, 0, 0, 0, 0, 0, 16, -5250, 120, 2], ["18 Sep", 5, "MUN(A) 1-3", 45, 0, 0, 0, 3, 0, 0, 0, 0, 0, 0, 0, -6, -10428, 119, 1], ["24 Sep", 6, "SWA(H) 4-1", 0, 0, 0, 0, 0, 0, 0, 0, 0, 0, 0, 0, 0, -7377, 118, 0], ["02 Oct", 7, "BOL(A) 5-1", 90, 3, 0, 0, 1, 0, 0, 0, 0, 0, 0, 3, 71, -8962, 117, 20], ["15 Oct", 8, "EVE(H) 3-1", 90, 0, 1, 0, 1, 0, 0, 0, 0, 0, 0, 1, 29, 23367, 116, 6], ["23 Oct", 9, "QPR(A) 0-1", 90, 0, 0, 0, 1, 0, 0, 0, 1, 0, 0, 0, -3, 21387, 117, 1], ["29 Oct", 10, "ARS(H) 3-5", 90, 1, 1, 0, 5, 0, 0, 0, 0, 0, 0, 0, 28, -9546, 117, 10], ["05 Nov", 11, "BLA(A) 1-0", 90, 1, 0, 1, 0, 0, 0, 0, 0, 0, 0, 3, 44, 12139, 117, 11], ["20 Nov", 12, "LIV(H) 1-2", 90, 0, 0, 0, 2, 0, 0, 0, 0, 0, 0, 0, 2, 12829, 117, 2], ["26 Nov", 13, "WOL(H) 3-0", 21, 0, 0, 0, 0, 0, 0, 0, 0, 0, 0, 0, 5, 12738, 117, 1], ["03 Dec", 14, "NEW(A) 3-0", 59, 0, 0, 0, 0, 0, 0, 1, 0, 0, 0, 0, 6, -18489, 117, -1], ["12 Dec", 15, "MCI(H) 2-1", 18, 1, 0, 0, 0, 0, 0, 0, 0, 0, 0, 0, 16, -24227, 115, 6], ["17 Dec", 16, "WIG(A) 1-1", 90, 0, 0, 0, 1, 0, 0, 0, 0, 0, 0, 0, 10, -5004, 114, 2], ["22 Dec", 17, "TOT(A) 1-1", 0, 0, 0, 0, 0, 0, 0, 0, 0, 0, 0, 0, 0, -4732, 113, 0], ["26 Dec", 18, "FUL(H) 1-1", 60, 0, 0, 0, 1, 0, 0, 0, 0, 0, 0, 0, 6, -7809, 112, 2], ["31 Dec", 19, "AVL(H) 1-3", 34, 0, 0, 0, 2, 0, 0, 0, 0, 0, 0, 0, 3, -5187, 111, 1], ["02 Jan", 20, "WOL(A) 2-1", 90, 1, 0, 0, 1, 0, 0, 0, 1, 0, 0, 2, 34, -2577, 111, 8], ["14 Jan", 21, "SUN(H) 1-0", 72, 1, 0, 1, 0, 0, 0, 0, 0, 0, 0, 0, 18, 713, 111, 8], ["21 Jan", 22, "NOR(A) 0-0", 36, 0, 0, 0, 0, 0, 0, 0, 0, 0, 0, 0, 4, 15076, 111, 1], ["31 Jan", 23, "SWA(A) 1-1", 0, 0, 0, 0, 0, 0, 0, 0, 0, 0, 0, 0, 0, -16887, 111, 0], ["05 Feb", 24, "MUN(H) 3-3", 0, 0, 0, 0, 0, 0, 0, 0, 0, 0, 0, 0, 0, -4906, 110, 0], ["11 Feb", 25, "EVE(A) 0-2", 90, 0, 0, 0, 2, 0, 0, 0, 0, 0, 0, 0, 4, -3676, 110, 2], ["25 Feb", 26, "BOL(H) 3-0", 90, 1, 1, 1, 0, 0, 0, 0, 0, 0, 0, 3, 51, 253, 110, 14], ["03 Mar", 27, "WBA(A) 0-1", 90, 0, 0, 0, 1, 0, 0, 0, 0, 0, 0, 0, 1, 4355, 110, 2], ["10 Mar", 28, "STO(H) 1-0", 90, 0, 0, 1, 0, 0, 0, 0, 0, 0, 0, 1, 29, -204, 110, 4], ["21 Mar", 29, "MCI(A) 1-2", 90, 0, 0, 0, 2, 0, 0, 0, 1, 0, 0, 0, 10, 199, 110, 1], ["24 Mar", 30, "TOT(H) 0-0", 90, 0, 0, 1, 0, 0, 0, 0, 0, 0, 0, 0, 14, 990, 110, 3], ["31 Mar", 31, "AVL(A) 4-2", 90, 0, 0, 0, 2, 0, 0, 0, 0, 0, 0, 0, 15, 106, 110, 2], ["07 Apr", 32, "WIG(H) 2-1", 0, 0, 0, 0, 0, 0, 0, 0, 0, 0, 0, 0, 0, 830, 110, 0], ["09 Apr", 33, "FUL(A) 1-1", 90, 1, 0, 0, 1, 0, 0, 0, 0, 0, 0, 0, 10, -3335, 110, 7], ["21 Apr", 35, "ARS(A) 0-0", 0, 0, 0, 0, 0, 0, 0, 0, 0, 0, 0, 0, 0, 569, 110, 0], ["29 Apr", 36, "QPR(H) 6-1", 90, 0, 0, 0, 1, 0, 0, 0, 0, 0, 0, 0, 21, 18567, 110, 2], ["02 May", 36, "NEW(H) 0-2", 13, 0, 0, 0, 1, 0, 0, 0, 0, 0, 0, 0, -6, 18567, 110, 1], ["08 May", 37, "LIV(A) 1-4", 0, 0, 0, 0, 0, 0, 0, 0, 0, 0, 0, 0, 0, -8151, 110, 0], ["13 May", 38, "BLA(H) 2-1", 0, 0, 0, 0, 0, 0, 0, 0, 0, 0, 0, 0, 0, -2110, 110, 0]], "summary": [[36, "NEW (H)", 1], [37, "LIV (A)", 0], [38, "BLA (H)", 0]]}, "next_fixture": "", "transfers_in_event": 65, "selected_by": "2.7", "team_id": 5, "second_name": "Lampard", "photo_mobile_url": "http://cdn.ismfg.net/static/plfpl/img/shirts/photos/23277.jpg"}