{"transfers_out": 292906, "code": 294839, "event_total": 2, "last_season_points": 0, "squad_number": null, "transfers_balance": 15774, "news_updated": "2012-04-05T11:30:21 UTC+0000", "event_cost": 91, "news_added": "2012-04-01T20:00:32 UTC+0000", "web_name": "Nasri", "in_dreamteam": false, "team_code": 294839, "id": 20, "shirt_image_url": "http://cdn.ismfg.net/static/plfpl/img/shirts/shirt_9.png", "first_name": "Samir", "transfers_out_event": 22, "element_type_id": 3, "max_cost": 96, "event_explain": [["Minutes played", 90, 2]], "selected": 118870, "min_cost": 91, "fixtures": {"all": [], "summary": []}, "season_history": [["2008/09", 2398, 6, 2, 0, 26, 0, 0, 0, 4, 0, 0, 12, 0, 76, 112], ["2009/10", 1880, 2, 4, 0, 25, 0, 0, 0, 2, 0, 0, 9, 0, 76, 83], ["2010/11", 2383, 10, 1, 9, 28, 0, 0, 0, 4, 0, 0, 20, 0, 82, 134]], "total_points": 134, "type_name": "Midfielder", "team_name": "Man City", "status": "a", "added": "2011-07-14T10:25:53 UTC+0000", "form": 2.7, "shirt_mobile_image_url": "http://cdn.ismfg.net/static/plfpl/img/shirts/mobile/shirt_9.png", "current_fixture": "QPR (H)", "now_cost": 91, "points_per_game": 4.3, "transfers_in": 299205, "news": "", "original_cost": 95, "event_points": 2, "news_return": null, "fixture_history": {"all": [["13 Aug", 1, "NEW(A) 0-0", 0, 0, 0, 0, 0, 0, 0, 0, 0, 0, 0, 0, 0, 0, 95, 0], ["20 Aug", 2, "LIV(H) 0-2", 90, 0, 0, 0, 2, 0, 0, 0, 0, 0, 0, 0, 2, 0, 95, 2], ["28 Aug", 3, "TOT(A) 5-1", 90, 0, 3, 0, 1, 0, 0, 0, 0, 0, 0, 2, 44, 705, 95, 13], ["10 Sep", 4, "WIG(H) 3-0", 30, 0, 1, 0, 0, 0, 0, 0, 0, 0, 0, 0, 13, 85472, 96, 4], ["18 Sep", 5, "FUL(A) 2-2", 80, 0, 0, 0, 2, 0, 0, 0, 0, 0, 0, 0, 11, 17266, 96, 2], ["24 Sep", 6, "EVE(H) 2-0", 82, 0, 0, 1, 0, 0, 0, 0, 0, 0, 0, 0, 17, -9603, 96, 3], ["01 Oct", 7, "BLA(A) 4-0", 64, 1, 2, 1, 0, 0, 0, 0, 0, 0, 0, 3, 41, -16723, 96, 17], ["15 Oct", 8, "AVL(H) 4-1", 0, 0, 0, 0, 0, 0, 0, 0, 0, 0, 0, 0, 0, 47426, 96, 0], ["23 Oct", 9, "MUN(A) 6-1", 16, 0, 0, 0, 1, 0, 0, 0, 0, 0, 0, 0, 3, -12952, 96, 1], ["29 Oct", 10, "WOL(H) 3-1", 69, 0, 0, 1, 0, 0, 0, 0, 0, 0, 0, 0, 13, -31915, 96, 3], ["05 Nov", 11, "QPR(A) 3-2", 0, 0, 0, 0, 0, 0, 0, 0, 0, 0, 0, 0, 0, -7014, 95, 0], ["19 Nov", 12, "NEW(H) 3-1", 90, 0, 0, 0, 1, 0, 0, 0, 0, 0, 0, 0, 14, -35235, 94, 2], ["27 Nov", 13, "LIV(A) 1-1", 64, 0, 0, 0, 1, 0, 0, 0, 0, 0, 0, 0, 8, -14500, 93, 2], ["03 Dec", 14, "NOR(H) 5-1", 68, 1, 0, 1, 0, 0, 0, 0, 0, 0, 0, 1, 29, -7333, 93, 9], ["12 Dec", 15, "CHE(A) 1-2", 0, 0, 0, 0, 0, 0, 0, 0, 0, 0, 0, 0, 0, -2742, 92, 0], ["18 Dec", 16, "ARS(H) 1-0", 84, 0, 0, 1, 0, 0, 0, 0, 0, 0, 0, 0, 15, -5157, 92, 3], ["21 Dec", 17, "STO(H) 3-0", 90, 0, 1, 1, 0, 0, 0, 0, 0, 0, 0, 1, 23, -464, 92, 7], ["26 Dec", 18, "WBA(A) 0-0", 58, 0, 0, 0, 0, 0, 0, 0, 0, 0, 0, 0, 8, -938, 92, 1], ["01 Jan", 19, "SUN(A) 0-1", 54, 0, 0, 0, 0, 0, 0, 0, 0, 0, 0, 0, 1, -3441, 91, 1], ["03 Jan", 20, "LIV(H) 3-0", 0, 0, 0, 0, 0, 0, 0, 0, 0, 0, 0, 0, 0, -1912, 91, 0], ["16 Jan", 21, "WIG(A) 1-0", 73, 0, 0, 1, 0, 0, 0, 0, 0, 0, 0, 0, 16, -2230, 91, 3], ["22 Jan", 22, "TOT(H) 3-2", 90, 1, 0, 0, 2, 0, 0, 0, 0, 0, 0, 2, 35, -1986, 91, 9], ["31 Jan", 23, "EVE(A) 0-1", 90, 0, 0, 0, 1, 0, 0, 0, 0, 0, 0, 0, -7, 2526, 91, 2], ["04 Feb", 24, "FUL(H) 3-0", 53, 0, 0, 0, 0, 0, 0, 0, 0, 0, 0, 0, 10, 4097, 91, 1], ["12 Feb", 25, "AVL(A) 1-0", 7, 0, 0, 0, 0, 0, 0, 0, 0, 0, 0, 0, 1, -9727, 91, 1], ["25 Feb", 26, "BLA(H) 3-0", 0, 0, 0, 0, 0, 0, 0, 0, 0, 0, 0, 0, 0, -1370, 91, 0], ["03 Mar", 27, "BOL(H) 2-0", 83, 0, 0, 1, 0, 0, 0, 0, 0, 0, 0, 0, 12, -1362, 91, 3], ["11 Mar", 28, "SWA(A) 0-1", 90, 0, 0, 0, 1, 0, 0, 0, 0, 0, 0, 0, 18, -1386, 91, 2], ["21 Mar", 29, "CHE(H) 2-1", 90, 1, 0, 0, 1, 0, 0, 0, 1, 0, 0, 3, 23, -983, 91, 9], ["24 Mar", 30, "STO(A) 1-1", 90, 0, 0, 0, 1, 0, 0, 0, 0, 0, 0, 0, 11, 4609, 91, 2], ["31 Mar", 31, "SUN(H) 3-3", 0, 0, 0, 0, 0, 0, 0, 0, 0, 0, 0, 0, 0, 2911, 91, 0], ["08 Apr", 32, "ARS(A) 0-1", 78, 0, 0, 1, 0, 0, 0, 0, 0, 0, 0, 0, 4, -5286, 91, 3], ["11 Apr", 33, "WBA(H) 4-0", 90, 0, 2, 1, 0, 0, 0, 0, 0, 0, 0, 0, 16, 597, 91, 9], ["14 Apr", 34, "NOR(A) 6-1", 62, 0, 0, 0, 1, 0, 0, 0, 1, 0, 0, 0, 7, 9131, 91, 1], ["22 Apr", 35, "WOL(A) 2-0", 85, 1, 0, 1, 0, 0, 0, 0, 0, 0, 0, 3, 28, -3053, 91, 11], ["30 Apr", 36, "MUN(H) 1-0", 90, 0, 0, 1, 0, 0, 0, 0, 0, 0, 0, 0, 13, -306, 91, 3], ["06 May", 37, "NEW(A) 2-0", 60, 0, 0, 1, 0, 0, 0, 0, 0, 0, 0, 0, 4, 2249, 91, 3], ["13 May", 38, "QPR(H) 3-2", 90, 0, 0, 0, 2, 0, 0, 0, 0, 0, 0, 0, 7, 6443, 91, 2]], "summary": [[36, "MUN (H)", 3], [37, "NEW (A)", 3], [38, "QPR (H)", 2]]}, "next_fixture": "", "transfers_in_event": 275, "selected_by": "4.3", "team_id": 9, "second_name": "Nasri", "photo_mobile_url": "http://cdn.ismfg.net/static/plfpl/img/shirts/photos/294839.jpg"}