{"transfers_out": 151817, "code": 303162, "event_total": 0, "last_season_points": 0, "squad_number": null, "transfers_balance": -178, "news_updated": "2012-03-16T11:30:27 UTC+0000", "event_cost": 55, "news_added": "2012-05-04T10:00:28 UTC+0000", "web_name": "Bendtner", "in_dreamteam": false, "team_code": 303162, "id": 22, "shirt_image_url": "http://cdn.ismfg.net/static/plfpl/img/shirts/shirt_15.png", "first_name": "Nicklas", "transfers_out_event": 53, "element_type_id": 4, "max_cost": 65, "event_explain": [["Minutes played", 0, 0]], "selected": 30320, "min_cost": 55, "fixtures": {"all": [], "summary": []}, "season_history": [["2007/08", 945, 5, 3, 0, 10, 0, 0, 0, 1, 1, 0, 4, 0, 54, 63], ["2008/09", 1765, 9, 2, 0, 15, 0, 0, 0, 1, 0, 0, 8, 0, 56, 97], ["2009/10", 1234, 6, 6, 0, 13, 0, 0, 0, 2, 0, 0, 5, 0, 57, 79], ["2010/11", 509, 2, 2, 2, 5, 0, 0, 0, 2, 0, 0, 0, 0, 63, 32]], "total_points": 116, "type_name": "Forward", "team_name": "Sunderland", "status": "a", "added": "2011-07-14T10:25:53 UTC+0000", "form": 0.5, "shirt_mobile_image_url": "http://cdn.ismfg.net/static/plfpl/img/shirts/mobile/shirt_15.png", "current_fixture": "Man Utd (H)", "now_cost": 55, "points_per_game": 4.0, "transfers_in": 165942, "news": "", "original_cost": 65, "event_points": 0, "news_return": "2012-02-11T18:00:19 UTC+0000", "fixture_history": {"all": [["13 Aug", 1, "NEW(A) 0-0", 0, 0, 0, 0, 0, 0, 0, 0, 0, 0, 0, 0, 0, 0, 65, 0], ["20 Aug", 2, "LIV(H) 0-2", 11, 0, 0, 0, 1, 0, 0, 0, 0, 0, 0, 0, 1, 0, 65, 1], ["28 Aug", 3, "MUN(A) 2-8", 0, 0, 0, 0, 0, 0, 0, 0, 0, 0, 0, 0, 0, -635, 65, 0], ["10 Sep", 4, "CHE(H) 1-2", 90, 0, 1, 0, 2, 0, 0, 0, 0, 0, 0, 0, 3, 5763, 64, 5], ["18 Sep", 5, "STO(H) 4-0", 84, 0, 1, 1, 0, 0, 0, 0, 0, 0, 0, 0, 23, 5650, 64, 5], ["26 Sep", 6, "NOR(A) 1-2", 90, 0, 0, 0, 2, 0, 0, 0, 0, 0, 0, 0, 9, 6633, 64, 2], ["01 Oct", 7, "WBA(H) 2-2", 90, 1, 1, 0, 2, 0, 0, 0, 0, 0, 0, 3, 46, 2578, 64, 12], ["16 Oct", 8, "ARS(A) 1-2", 0, 0, 0, 0, 0, 0, 0, 0, 0, 0, 0, 0, 0, -8779, 64, 0], ["22 Oct", 9, "BOL(A) 2-0", 90, 1, 0, 1, 0, 0, 0, 0, 0, 0, 0, 2, 38, -380, 64, 8], ["29 Oct", 10, "AVL(H) 2-2", 90, 0, 0, 0, 2, 0, 0, 0, 0, 0, 0, 0, 2, 11877, 64, 2], ["05 Nov", 11, "MUN(A) 0-1", 90, 0, 0, 0, 1, 0, 0, 0, 0, 0, 0, 0, 9, -4032, 64, 2], ["19 Nov", 12, "FUL(H) 0-0", 90, 0, 0, 1, 0, 0, 0, 0, 0, 0, 0, 1, 15, 13265, 64, 3], ["26 Nov", 13, "WIG(H) 1-2", 90, 0, 0, 0, 2, 0, 0, 0, 0, 0, 0, 0, -5, 5706, 64, 2], ["04 Dec", 14, "WOL(A) 1-2", 90, 0, 0, 0, 2, 0, 0, 0, 1, 0, 0, 0, -10, -9610, 64, 1], ["11 Dec", 15, "BLA(H) 2-1", 0, 0, 0, 0, 0, 0, 0, 0, 0, 0, 0, 0, 0, -11414, 64, 0], ["18 Dec", 16, "TOT(A) 0-1", 45, 0, 0, 0, 1, 0, 0, 0, 0, 0, 0, 0, 3, -9545, 62, 1], ["21 Dec", 17, "QPR(A) 3-2", 90, 1, 0, 0, 2, 0, 0, 0, 0, 0, 0, 0, 15, -1393, 62, 6], ["26 Dec", 18, "EVE(H) 1-1", 90, 0, 0, 0, 1, 0, 0, 0, 0, 0, 0, 0, 0, 1312, 62, 2], ["01 Jan", 19, "MCI(H) 1-0", 77, 0, 0, 1, 0, 0, 0, 0, 0, 0, 0, 0, 16, -726, 62, 2], ["03 Jan", 20, "WIG(A) 4-1", 90, 0, 2, 0, 1, 0, 0, 0, 0, 0, 0, 0, 23, 127, 62, 8], ["14 Jan", 21, "CHE(A) 0-1", 90, 0, 0, 0, 1, 0, 0, 0, 0, 0, 0, 0, 1, 3434, 62, 2], ["21 Jan", 22, "SWA(H) 2-0", 11, 0, 0, 0, 0, 0, 0, 0, 0, 0, 0, 0, 2, 15375, 62, 1], ["01 Feb", 23, "NOR(H) 3-0", 0, 0, 0, 0, 0, 0, 0, 0, 0, 0, 0, 0, 0, -14361, 62, 0], ["04 Feb", 24, "STO(A) 1-0", 0, 0, 0, 0, 0, 0, 0, 0, 0, 0, 0, 0, 0, -5752, 62, 0], ["11 Feb", 25, "ARS(H) 1-2", 0, 0, 0, 0, 0, 0, 0, 0, 0, 0, 0, 0, 0, -2702, 61, 0], ["25 Feb", 26, "WBA(A) 0-4", 45, 0, 0, 0, 2, 0, 0, 0, 0, 0, 0, 0, 2, -206, 61, 1], ["04 Mar", 27, "NEW(A) 1-1", 70, 1, 0, 1, 0, 0, 0, 0, 0, 0, 0, 3, 24, -434, 61, 9], ["10 Mar", 28, "LIV(H) 1-0", 82, 1, 0, 1, 0, 0, 0, 0, 0, 0, 0, 3, 34, 282, 61, 9], ["20 Mar", 29, "BLA(A) 0-2", 90, 0, 0, 0, 2, 0, 0, 0, 0, 0, 0, 0, 6, 585, 61, 2], ["24 Mar", 30, "QPR(H) 3-1", 81, 1, 0, 0, 1, 0, 0, 0, 0, 0, 0, 1, 27, 4305, 61, 7], ["31 Mar", 31, "MCI(A) 3-3", 90, 1, 1, 0, 3, 0, 0, 0, 0, 0, 0, 1, 26, 1930, 61, 10], ["07 Apr", 32, "TOT(H) 0-0", 90, 0, 0, 1, 0, 0, 0, 0, 0, 0, 0, 0, 3, 16206, 61, 2], ["09 Apr", 33, "EVE(A) 0-4", 0, 0, 0, 0, 0, 0, 0, 0, 0, 0, 0, 0, 0, -781, 62, 0], ["14 Apr", 34, "WOL(H) 0-0", 90, 0, 0, 1, 0, 0, 0, 0, 0, 0, 0, 0, 4, 23928, 62, 2], ["21 Apr", 35, "AVL(A) 0-0", 79, 0, 0, 1, 0, 0, 0, 0, 1, 0, 0, 0, -2, -15646, 61, 1], ["28 Apr", 36, "BOL(H) 2-2", 90, 1, 0, 0, 2, 0, 0, 0, 0, 0, 0, 1, 22, -12898, 58, 7], ["06 May", 37, "FUL(A) 1-2", 31, 0, 0, 0, 0, 0, 0, 0, 0, 0, 0, 0, -3, -3282, 57, 1], ["13 May", 38, "MUN(H) 0-1", 0, 0, 0, 0, 0, 0, 0, 0, 0, 0, 0, 0, 0, -2127, 55, 0]], "summary": [[36, "BOL (H)", 7], [37, "FUL (A)", 1], [38, "MUN (H)", 0]]}, "next_fixture": "", "transfers_in_event": 5, "selected_by": "1.1", "team_id": 15, "second_name": "Bendtner", "photo_mobile_url": "http://cdn.ismfg.net/static/plfpl/img/shirts/photos/303162.jpg"}