{"transfers_out": 1326, "code": 266190, "event_total": 0, "last_season_points": 0, "squad_number": null, "transfers_balance": 339, "news_updated": "2012-01-01T15:15:11 UTC+0000", "event_cost": 39, "news_added": "2011-08-08T19:45:03 UTC+0000", "web_name": "Angeleri", "in_dreamteam": false, "team_code": 266190, "id": 336, "shirt_image_url": "http://cdn.ismfg.net/static/plfpl/img/shirts/shirt_15.png", "first_name": "Marcos", "transfers_out_event": 0, "element_type_id": 2, "max_cost": 40, "event_explain": [["Minutes played", 0, 0]], "selected": 1939, "min_cost": 39, "fixtures": {"all": [], "summary": []}, "season_history": [["2010/11", 9, 0, 0, 0, 0, 0, 0, 0, 0, 0, 0, 0, 0, 44, 2]], "total_points": 0, "type_name": "Defender", "team_name": "Sunderland", "status": "i", "added": "2011-07-14T10:25:57 UTC+0000", "form": 0.0, "shirt_mobile_image_url": "http://cdn.ismfg.net/static/plfpl/img/shirts/mobile/shirt_15.png", "current_fixture": "Man Utd (H)", "now_cost": 39, "points_per_game": 0.0, "transfers_in": 1579, "news": "Knee injury - Unknown return date", "original_cost": 40, "event_points": 0, "news_return": null, "fixture_history": {"all": [["13 Aug", 1, "LIV(A) 1-1", 0, 0, 0, 0, 0, 0, 0, 0, 0, 0, 0, 0, 0, 0, 40, 0], ["20 Aug", 2, "NEW(H) 0-1", 0, 0, 0, 0, 0, 0, 0, 0, 0, 0, 0, 0, 0, 0, 40, 0], ["27 Aug", 3, "SWA(A) 0-0", 0, 0, 0, 0, 0, 0, 0, 0, 0, 0, 0, 0, 0, -76, 40, 0], ["10 Sep", 4, "CHE(H) 1-2", 0, 0, 0, 0, 0, 0, 0, 0, 0, 0, 0, 0, 0, -81, 40, 0], ["18 Sep", 5, "STO(H) 4-0", 0, 0, 0, 0, 0, 0, 0, 0, 0, 0, 0, 0, 0, -35, 40, 0], ["26 Sep", 6, "NOR(A) 1-2", 0, 0, 0, 0, 0, 0, 0, 0, 0, 0, 0, 0, 0, -33, 40, 0], ["01 Oct", 7, "WBA(H) 2-2", 0, 0, 0, 0, 0, 0, 0, 0, 0, 0, 0, 0, 0, -22, 40, 0], ["16 Oct", 8, "ARS(A) 1-2", 0, 0, 0, 0, 0, 0, 0, 0, 0, 0, 0, 0, 0, -18, 40, 0], ["22 Oct", 9, "BOL(A) 2-0", 0, 0, 0, 0, 0, 0, 0, 0, 0, 0, 0, 0, 0, -5, 40, 0], ["29 Oct", 10, "AVL(H) 2-2", 0, 0, 0, 0, 0, 0, 0, 0, 0, 0, 0, 0, 0, -21, 40, 0], ["05 Nov", 11, "MUN(A) 0-1", 0, 0, 0, 0, 0, 0, 0, 0, 0, 0, 0, 0, 0, -15, 40, 0], ["19 Nov", 12, "FUL(H) 0-0", 0, 0, 0, 0, 0, 0, 0, 0, 0, 0, 0, 0, 0, -2, 40, 0], ["26 Nov", 13, "WIG(H) 1-2", 0, 0, 0, 0, 0, 0, 0, 0, 0, 0, 0, 0, 0, -8, 40, 0], ["04 Dec", 14, "WOL(A) 1-2", 0, 0, 0, 0, 0, 0, 0, 0, 0, 0, 0, 0, 0, -12, 40, 0], ["11 Dec", 15, "BLA(H) 2-1", 0, 0, 0, 0, 0, 0, 0, 0, 0, 0, 0, 0, 0, 6, 40, 0], ["18 Dec", 16, "TOT(A) 0-1", 0, 0, 0, 0, 0, 0, 0, 0, 0, 0, 0, 0, 0, -14, 40, 0], ["21 Dec", 17, "QPR(A) 3-2", 0, 0, 0, 0, 0, 0, 0, 0, 0, 0, 0, 0, 0, 12, 39, 0], ["26 Dec", 18, "EVE(H) 1-1", 0, 0, 0, 0, 0, 0, 0, 0, 0, 0, 0, 0, 0, 45, 39, 0], ["01 Jan", 19, "MCI(H) 1-0", 0, 0, 0, 0, 0, 0, 0, 0, 0, 0, 0, 0, 0, 19, 39, 0], ["03 Jan", 20, "WIG(A) 4-1", 0, 0, 0, 0, 0, 0, 0, 0, 0, 0, 0, 0, 0, 13, 39, 0], ["14 Jan", 21, "CHE(A) 0-1", 0, 0, 0, 0, 0, 0, 0, 0, 0, 0, 0, 0, 0, 132, 39, 0], ["21 Jan", 22, "SWA(H) 2-0", 0, 0, 0, 0, 0, 0, 0, 0, 0, 0, 0, 0, 0, 28, 39, 0], ["01 Feb", 23, "NOR(H) 3-0", 0, 0, 0, 0, 0, 0, 0, 0, 0, 0, 0, 0, 0, 16, 39, 0], ["04 Feb", 24, "STO(A) 1-0", 0, 0, 0, 0, 0, 0, 0, 0, 0, 0, 0, 0, 0, -16, 39, 0], ["11 Feb", 25, "ARS(H) 1-2", 0, 0, 0, 0, 0, 0, 0, 0, 0, 0, 0, 0, 0, -5, 39, 0], ["25 Feb", 26, "WBA(A) 0-4", 0, 0, 0, 0, 0, 0, 0, 0, 0, 0, 0, 0, 0, 57, 39, 0], ["04 Mar", 27, "NEW(A) 1-1", 0, 0, 0, 0, 0, 0, 0, 0, 0, 0, 0, 0, 0, 37, 39, 0], ["10 Mar", 28, "LIV(H) 1-0", 0, 0, 0, 0, 0, 0, 0, 0, 0, 0, 0, 0, 0, -6, 39, 0], ["20 Mar", 29, "BLA(A) 0-2", 0, 0, 0, 0, 0, 0, 0, 0, 0, 0, 0, 0, 0, -10, 39, 0], ["24 Mar", 30, "QPR(H) 3-1", 0, 0, 0, 0, 0, 0, 0, 0, 0, 0, 0, 0, 0, -7, 39, 0], ["31 Mar", 31, "MCI(A) 3-3", 0, 0, 0, 0, 0, 0, 0, 0, 0, 0, 0, 0, 0, -3, 39, 0], ["07 Apr", 32, "TOT(H) 0-0", 0, 0, 0, 0, 0, 0, 0, 0, 0, 0, 0, 0, 0, 12, 39, 0], ["09 Apr", 33, "EVE(A) 0-4", 0, 0, 0, 0, 0, 0, 0, 0, 0, 0, 0, 0, 0, 20, 39, 0], ["14 Apr", 34, "WOL(H) 0-0", 0, 0, 0, 0, 0, 0, 0, 0, 0, 0, 0, 0, 0, 23, 39, 0], ["21 Apr", 35, "AVL(A) 0-0", 0, 0, 0, 0, 0, 0, 0, 0, 0, 0, 0, 0, 0, 52, 39, 0], ["28 Apr", 36, "BOL(H) 2-2", 0, 0, 0, 0, 0, 0, 0, 0, 0, 0, 0, 0, 0, 7, 39, 0], ["06 May", 37, "FUL(A) 1-2", 0, 0, 0, 0, 0, 0, 0, 0, 0, 0, 0, 0, 0, 52, 39, 0], ["13 May", 38, "MUN(H) 0-1", 0, 0, 0, 0, 0, 0, 0, 0, 0, 0, 0, 0, 0, 108, 39, 0]], "summary": [[36, "BOL (H)", 0], [37, "FUL (A)", 0], [38, "MUN (H)", 0]]}, "next_fixture": "", "transfers_in_event": 3, "selected_by": "0.1", "team_id": 15, "second_name": "Angeleri", "photo_mobile_url": "http://cdn.ismfg.net/static/plfpl/img/shirts/photos/266190.jpg"}