{"transfers_out": 14165, "code": 377777, "event_total": 0, "last_season_points": 0, "squad_number": null, "transfers_balance": -73, "news_updated": "2012-04-13T11:30:25 UTC+0000", "event_cost": 50, "news_added": "2012-01-20T13:00:08 UTC+0000", "web_name": "Delph", "in_dreamteam": false, "team_code": 377777, "id": 38, "shirt_image_url": "http://cdn.ismfg.net/static/plfpl/img/shirts/shirt_2.png", "first_name": "Fabian", "transfers_out_event": 0, "element_type_id": 3, "max_cost": 55, "event_explain": [["Minutes played", 0, 0]], "selected": 5914, "min_cost": 50, "fixtures": {"all": [], "summary": []}, "season_history": [["2009/10", 291, 0, 0, 0, 6, 0, 0, 0, 3, 0, 0, 0, 0, 50, 8], ["2010/11", 414, 0, 0, 0, 7, 0, 0, 0, 1, 0, 0, 0, 0, 50, 9]], "total_points": 22, "type_name": "Midfielder", "team_name": "Aston Villa", "status": "d", "added": "2011-07-14T10:25:53 UTC+0000", "form": 0.0, "shirt_mobile_image_url": "http://cdn.ismfg.net/static/plfpl/img/shirts/mobile/shirt_2.png", "current_fixture": "Norwich (A)", "now_cost": 50, "points_per_game": 2.0, "transfers_in": 4902, "news": "Ankle injury - 75% chance of playing", "original_cost": 55, "event_points": 0, "news_return": null, "fixture_history": {"all": [["13 Aug", 1, "FUL(A) 0-0", 90, 0, 0, 1, 0, 0, 0, 0, 0, 0, 0, 0, 9, 0, 55, 3], ["20 Aug", 2, "BLA(H) 3-1", 90, 0, 0, 0, 1, 0, 0, 0, 1, 0, 0, 0, 19, 0, 55, 1], ["27 Aug", 3, "WOL(H) 0-0", 83, 0, 0, 1, 0, 0, 0, 0, 1, 0, 0, 0, 8, -329, 55, 2], ["10 Sep", 4, "EVE(A) 2-2", 79, 0, 0, 0, 2, 0, 0, 0, 0, 0, 0, 0, 7, -1593, 55, 2], ["17 Sep", 5, "NEW(H) 1-1", 90, 0, 0, 0, 1, 0, 0, 0, 0, 0, 0, 0, 8, -419, 54, 2], ["25 Sep", 6, "QPR(A) 1-1", 90, 0, 0, 0, 1, 0, 0, 0, 0, 0, 0, 0, 5, -661, 54, 2], ["01 Oct", 7, "WIG(H) 2-0", 90, 0, 0, 1, 0, 0, 0, 0, 0, 0, 0, 0, 12, -540, 54, 3], ["15 Oct", 8, "MCI(A) 1-4", 75, 0, 0, 0, 4, 0, 0, 0, 0, 0, 0, 0, 6, -694, 53, 2], ["22 Oct", 9, "WBA(H) 1-2", 0, 0, 0, 0, 0, 0, 0, 0, 0, 0, 0, 0, 0, -326, 53, 0], ["29 Oct", 10, "SUN(A) 2-2", 0, 0, 0, 0, 0, 0, 0, 0, 0, 0, 0, 0, 0, -1171, 52, 0], ["05 Nov", 11, "NOR(H) 3-2", 0, 0, 0, 0, 0, 0, 0, 0, 0, 0, 0, 0, 0, -521, 52, 0], ["21 Nov", 12, "TOT(A) 0-2", 4, 0, 0, 0, 0, 0, 0, 0, 0, 0, 0, 0, 0, -508, 52, 1], ["27 Nov", 13, "SWA(A) 0-0", 78, 0, 0, 1, 0, 0, 0, 0, 1, 0, 0, 0, 7, -271, 51, 2], ["03 Dec", 14, "MUN(H) 0-1", 0, 0, 0, 0, 0, 0, 0, 0, 0, 0, 0, 0, 0, -110, 51, 0], ["10 Dec", 15, "BOL(A) 2-1", 0, 0, 0, 0, 0, 0, 0, 0, 0, 0, 0, 0, 0, -143, 51, 0], ["18 Dec", 16, "LIV(H) 0-2", 79, 0, 0, 0, 2, 0, 0, 0, 0, 0, 0, 0, -4, -318, 51, 2], ["21 Dec", 17, "ARS(H) 1-2", 0, 0, 0, 0, 0, 0, 0, 0, 0, 0, 0, 0, 0, -41, 51, 0], ["26 Dec", 18, "STO(A) 0-0", 0, 0, 0, 0, 0, 0, 0, 0, 0, 0, 0, 0, 0, -90, 51, 0], ["31 Dec", 19, "CHE(A) 3-1", 0, 0, 0, 0, 0, 0, 0, 0, 0, 0, 0, 0, 0, -87, 51, 0], ["02 Jan", 20, "SWA(H) 0-2", 0, 0, 0, 0, 0, 0, 0, 0, 0, 0, 0, 0, 0, -38, 51, 0], ["14 Jan", 21, "EVE(H) 1-1", 0, 0, 0, 0, 0, 0, 0, 0, 0, 0, 0, 0, 0, -264, 51, 0], ["21 Jan", 22, "WOL(A) 3-2", 0, 0, 0, 0, 0, 0, 0, 0, 0, 0, 0, 0, 0, -200, 51, 0], ["01 Feb", 23, "QPR(H) 2-2", 0, 0, 0, 0, 0, 0, 0, 0, 0, 0, 0, 0, 0, -284, 51, 0], ["05 Feb", 24, "NEW(A) 1-2", 0, 0, 0, 0, 0, 0, 0, 0, 0, 0, 0, 0, 0, -107, 51, 0], ["12 Feb", 25, "MCI(H) 0-1", 0, 0, 0, 0, 0, 0, 0, 0, 0, 0, 0, 0, 0, -137, 51, 0], ["25 Feb", 26, "WIG(A) 0-0", 0, 0, 0, 0, 0, 0, 0, 0, 0, 0, 0, 0, 0, -128, 51, 0], ["03 Mar", 27, "BLA(A) 1-1", 0, 0, 0, 0, 0, 0, 0, 0, 0, 0, 0, 0, 0, -38, 51, 0], ["10 Mar", 28, "FUL(H) 1-0", 0, 0, 0, 0, 0, 0, 0, 0, 0, 0, 0, 0, 0, -52, 51, 0], ["24 Mar", 30, "ARS(A) 0-3", 0, 0, 0, 0, 0, 0, 0, 0, 0, 0, 0, 0, 0, -37, 50, 0], ["31 Mar", 31, "CHE(H) 2-4", 0, 0, 0, 0, 0, 0, 0, 0, 0, 0, 0, 0, 0, -34, 50, 0], ["07 Apr", 32, "LIV(A) 1-1", 0, 0, 0, 0, 0, 0, 0, 0, 0, 0, 0, 0, 0, -14, 50, 0], ["09 Apr", 33, "STO(H) 1-1", 0, 0, 0, 0, 0, 0, 0, 0, 0, 0, 0, 0, 0, -4, 50, 0], ["15 Apr", 34, "MUN(A) 0-4", 0, 0, 0, 0, 0, 0, 0, 0, 0, 0, 0, 0, 0, -18, 50, 0], ["21 Apr", 35, "SUN(H) 0-0", 0, 0, 0, 0, 0, 0, 0, 0, 0, 0, 0, 0, 0, -15, 50, 0], ["24 Apr", 35, "BOL(H) 1-2", 0, 0, 0, 0, 0, 0, 0, 0, 0, 0, 0, 0, 0, -15, 50, 0], ["28 Apr", 36, "WBA(A) 0-0", 0, 0, 0, 0, 0, 0, 0, 0, 0, 0, 0, 0, 0, -13, 50, 0], ["06 May", 37, "TOT(H) 1-1", 0, 0, 0, 0, 0, 0, 0, 0, 0, 0, 0, 0, 0, -8, 50, 0], ["13 May", 38, "NOR(A) 0-2", 0, 0, 0, 0, 0, 0, 0, 0, 0, 0, 0, 0, 0, -5, 50, 0]], "summary": [[36, "WBA (A)", 0], [37, "TOT (H)", 0], [38, "NOR (A)", 0]]}, "next_fixture": "", "transfers_in_event": 0, "selected_by": "0.2", "team_id": 2, "second_name": "Delph", "photo_mobile_url": "http://cdn.ismfg.net/static/plfpl/img/shirts/photos/377777.jpg"}