{"transfers_out": 875, "code": 331404, "event_total": 0, "last_season_points": 0, "squad_number": null, "transfers_balance": 24, "news_updated": null, "event_cost": 41, "news_added": null, "web_name": "Amos", "in_dreamteam": false, "team_code": 331404, "id": 638, "shirt_image_url": "http://cdn.ismfg.net/static/plfpl/img/shirts/shirt_10_1.png", "first_name": "Ben", "transfers_out_event": 0, "element_type_id": 1, "max_cost": 45, "event_explain": [["Minutes played", 0, 0]], "selected": 814, "min_cost": 41, "fixtures": {"all": [], "summary": []}, "season_history": [["2008/09", 0, 0, 0, 0, 0, 0, 0, 0, 0, 0, 0, 0, 0, 39, 0], ["2009/10", 0, 0, 0, 0, 0, 0, 0, 0, 0, 0, 0, 0, 0, 45, 0], ["2010/11", 0, 0, 0, 0, 0, 0, 0, 0, 0, 0, 0, 0, 0, 45, 0]], "total_points": 6, "type_name": "Goalkeeper", "team_name": "Man Utd", "status": "a", "added": "2012-01-31T20:54:08 UTC+0000", "form": 0.0, "shirt_mobile_image_url": "http://cdn.ismfg.net/static/plfpl/img/shirts/mobile/shirt_10_1.png", "current_fixture": "Sunderland (A)", "now_cost": 41, "points_per_game": 6.0, "transfers_in": 1327, "news": "", "original_cost": 45, "event_points": 0, "news_return": null, "fixture_history": {"all": [["31 Jan", 23, "STO(H) 2-0", 90, 0, 0, 1, 0, 0, 0, 0, 0, 0, 1, 0, 16, 0, 45, 6], ["05 Feb", 24, "CHE(A) 3-3", 0, 0, 0, 0, 0, 0, 0, 0, 0, 0, 0, 0, 0, 617, 45, 0], ["11 Feb", 25, "LIV(H) 2-1", 0, 0, 0, 0, 0, 0, 0, 0, 0, 0, 0, 0, 0, -31, 45, 0], ["26 Feb", 26, "NOR(A) 2-1", 0, 0, 0, 0, 0, 0, 0, 0, 0, 0, 0, 0, 0, -43, 45, 0], ["04 Mar", 27, "TOT(A) 3-1", 0, 0, 0, 0, 0, 0, 0, 0, 0, 0, 0, 0, 0, -57, 43, 0], ["11 Mar", 28, "WBA(H) 2-0", 0, 0, 0, 0, 0, 0, 0, 0, 0, 0, 0, 0, 0, -26, 43, 0], ["18 Mar", 29, "WOL(A) 5-0", 0, 0, 0, 0, 0, 0, 0, 0, 0, 0, 0, 0, 0, -20, 42, 0], ["26 Mar", 30, "FUL(H) 1-0", 0, 0, 0, 0, 0, 0, 0, 0, 0, 0, 0, 0, 0, -15, 42, 0], ["02 Apr", 31, "BLA(A) 2-0", 0, 0, 0, 0, 0, 0, 0, 0, 0, 0, 0, 0, 0, -7, 41, 0], ["08 Apr", 32, "QPR(H) 2-0", 0, 0, 0, 0, 0, 0, 0, 0, 0, 0, 0, 0, 0, -7, 41, 0], ["11 Apr", 33, "WIG(A) 0-1", 0, 0, 0, 0, 0, 0, 0, 0, 0, 0, 0, 0, 0, 1, 41, 0], ["15 Apr", 34, "AVL(H) 4-0", 0, 0, 0, 0, 0, 0, 0, 0, 0, 0, 0, 0, 0, -8, 41, 0], ["22 Apr", 35, "EVE(H) 4-4", 0, 0, 0, 0, 0, 0, 0, 0, 0, 0, 0, 0, 0, 7, 41, 0], ["30 Apr", 36, "MCI(A) 0-1", 0, 0, 0, 0, 0, 0, 0, 0, 0, 0, 0, 0, 0, 7, 41, 0], ["06 May", 37, "SWA(H) 2-0", 0, 0, 0, 0, 0, 0, 0, 0, 0, 0, 0, 0, 0, 16, 41, 0], ["13 May", 38, "SUN(A) 1-0", 0, 0, 0, 0, 0, 0, 0, 0, 0, 0, 0, 0, 0, 18, 41, 0]], "summary": [[36, "MCI (A)", 0], [37, "SWA (H)", 0], [38, "SUN (A)", 0]]}, "next_fixture": "", "transfers_in_event": 0, "selected_by": "0.0", "team_id": 10, "second_name": "Amos", "photo_mobile_url": "http://cdn.ismfg.net/static/plfpl/img/shirts/photos/331404.jpg"}